{
    "total": [
        {
            "id": "100006823595681",
            "count": 58
        },
        {
            "id": "100034164293233",
            "count": 0
        },
        {
            "id": "100044570100031",
            "count": 2
        },
        {
            "id": "100058501508078",
            "count": 0
        },
        {
            "id": "100058859851518",
            "count": 148
        },
        {
            "id": "100063169809115",
            "count": 17
        },
        {
            "id": "100063526732400",
            "count": 33
        },
        {
            "id": "100065523518870",
            "count": 3
        },
        {
            "id": "100068783065668",
            "count": 432
        },
        {
            "id": "100070512833562",
            "count": 43
        },
        {
            "id": "100072280552150",
            "count": 0
        },
        {
            "id": "100073009375670",
            "count": 155
        },
        {
            "id": "100074636206904",
            "count": 3
        },
        {
            "id": "100075156273228",
            "count": 475
        },
        {
            "id": "100075238262160",
            "count": 204
        },
        {
            "id": "100075582905004",
            "count": 698
        },
        {
            "id": "100075747457384",
            "count": 44
        },
        {
            "id": "100077312576968",
            "count": 1
        },
        {
            "id": "100080153409719",
            "count": 0
        },
        {
            "id": "100080628871854",
            "count": 0
        },
        {
            "id": "100081040531210",
            "count": 187
        },
        {
            "id": "100083270917722",
            "count": 0
        },
        {
            "id": "100084425859178",
            "count": 0
        },
        {
            "id": "100084818654829",
            "count": 10
        }
    ],
    "week": [
        {
            "id": "100006823595681",
            "count": 23,
            "name": "Hoàng Khang"
        },
        {
            "id": "100034164293233",
            "count": 0,
            "name": "Viet Bui"
        },
        {
            "id": "100044570100031",
            "count": 0,
            "name": "Nguyễn Thị Thảo Hiền"
        },
        {
            "id": "100058501508078",
            "count": 0,
            "name": "Ng Khanh"
        },
        {
            "id": "100058859851518",
            "count": 11,
            "name": "Ngọc Như"
        },
        {
            "id": "100063169809115",
            "count": 16,
            "name": "Phạm Nam"
        },
        {
            "id": "100063526732400",
            "count": 0,
            "name": "Ng Thị Ngọc Như"
        },
        {
            "id": "100065523518870",
            "count": 1,
            "name": "Trang Dayy"
        },
        {
            "id": "100068783065668",
            "count": 62,
            "name": "Đinh Hữu Tình"
        },
        {
            "id": "100070512833562",
            "count": 9,
            "name": "Chau Thị Cẩm Tiên"
        },
        {
            "id": "100072280552150",
            "count": 0,
            "name": "Nugget Art"
        },
        {
            "id": "100073009375670",
            "count": 81,
            "name": "ʚDh Nqcutiɞ"
        },
        {
            "id": "100074636206904",
            "count": 1,
            "name": "Ng Yến Thi"
        },
        {
            "id": "100075156273228",
            "count": 134,
            "name": "Ng Hà Phương"
        },
        {
            "id": "100075238262160",
            "count": 29,
            "name": "Đình Tùng"
        },
        {
            "id": "100075582905004",
            "count": 87,
            "name": "Cậu Ba"
        },
        {
            "id": "100075747457384",
            "count": 1,
            "name": "Thắng Tony"
        },
        {
            "id": "100077312576968",
            "count": 0,
            "name": "Ph Minh Dat"
        },
        {
            "id": "100080153409719",
            "count": 0,
            "name": "Ng Phương Mai"
        },
        {
            "id": "100080628871854",
            "count": 0,
            "name": "Khánh Linh"
        },
        {
            "id": "100081040531210",
            "count": 18,
            "name": "Ngthp Nhicute"
        },
        {
            "id": "100083270917722",
            "count": 0,
            "name": "TrTh Diễm My"
        },
        {
            "id": "100084425859178",
            "count": 0,
            "name": "Tịch Nhi"
        },
        {
            "id": "100084818654829",
            "count": 10,
            "name": "Vương Ức Bồ Phương"
        }
    ],
    "day": [
        {
            "id": "100006823595681",
            "count": 0,
            "name": "Người dùng facebook"
        },
        {
            "id": "100034164293233",
            "count": 0,
            "name": "Người dùng facebook"
        },
        {
            "id": "100044570100031",
            "count": 0,
            "name": "Người dùng facebook"
        },
        {
            "id": "100058501508078",
            "count": 0,
            "name": "Người dùng facebook"
        },
        {
            "id": "100058859851518",
            "count": 0,
            "name": "Người dùng facebook"
        },
        {
            "id": "100063169809115",
            "count": 0,
            "name": "Người dùng facebook"
        },
        {
            "id": "100063526732400",
            "count": 0,
            "name": "Ng Thị Ngọc Như"
        },
        {
            "id": "100065523518870",
            "count": 0,
            "name": "Người dùng facebook"
        },
        {
            "id": "100068783065668",
            "count": 0,
            "name": "Đinh Hữu Tình"
        },
        {
            "id": "100070512833562",
            "count": 0,
            "name": "Người dùng facebook"
        },
        {
            "id": "100072280552150",
            "count": 0,
            "name": "Người dùng facebook"
        },
        {
            "id": "100073009375670",
            "count": 0,
            "name": "Người dùng facebook"
        },
        {
            "id": "100074636206904",
            "count": 0,
            "name": "Người dùng facebook"
        },
        {
            "id": "100075156273228",
            "count": 0,
            "name": "Người dùng facebook"
        },
        {
            "id": "100075238262160",
            "count": 0,
            "name": "Đình Tùng"
        },
        {
            "id": "100075582905004",
            "count": 0,
            "name": "Cậu Ba"
        },
        {
            "id": "100075747457384",
            "count": 0,
            "name": "Thắng Tony"
        },
        {
            "id": "100077312576968",
            "count": 0,
            "name": "Người dùng facebook"
        },
        {
            "id": "100080153409719",
            "count": 0,
            "name": "Người dùng facebook"
        },
        {
            "id": "100080628871854",
            "count": 0,
            "name": "Người dùng facebook"
        },
        {
            "id": "100081040531210",
            "count": 0,
            "name": "Người dùng facebook"
        },
        {
            "id": "100083270917722",
            "count": 0,
            "name": "Người dùng facebook"
        },
        {
            "id": "100084425859178",
            "count": 0,
            "name": "Người dùng facebook"
        },
        {
            "id": "100084818654829",
            "count": 0,
            "name": "Người dùng facebook"
        }
    ],
    "time": 2
}